MDContentAnalysis/ExampleUse.py
MDContentAnalysis/MDContentAnalysis.py
MDContentAnalysis/__init__.py
MDContentAnalysis/xmlMOLE.py
MDContentAnalysis-1.1.0.dist-info/LICENSE
MDContentAnalysis-1.1.0.dist-info/METADATA
MDContentAnalysis-1.1.0.dist-info/WHEEL
MDContentAnalysis-1.1.0.dist-info/top_level.txt
MDContentAnalysis-1.1.0.dist-info/RECORD
