Metadata-Version: 2.1
Name: MDContentAnalysis
Version: 1.1.0
Summary: Package for analysing content of protein channels/tunnel in molecular dynamics simulations. Analyses trajectories. Built upon MDAnalysis, and uses Hole 2.0 or Mole 2.5
Home-page: https://github.com/MartinWazar/MDContentAnalysis
Author: Martin Wazar Eriksen
Author-email: martin.wazar+GitHub@gmail.com
Classifier: Programming Language :: Python :: 3
Classifier: License :: OSI Approved :: MIT License
Classifier: Operating System :: OS Independent
License-File: LICENSE
Requires-Dist: MDAnalysis
